{
    "title": "文章",
    "description": "用于内容管理系统的文章",
    "name": "cms_article",
    "table": "cms_article",
    "key": "article_id",
    "fields": [
        {
            "name": "article_id",
            "title": "文章id",
            "description": "",
            "type": "mediumint",
            "key": true,
            "auto": "auto_increment",
            "symbol": false,
            "fill_zero": false,
            "not_null": 1,
            "min_length": 0,
            "max_length": 8,
            "min": 0,
            "max": 8388607,
            "decimal": 0,
            "default": "0",
            "map": ""
        },
        {
            "name": "img",
            "title": "封面图",
            "description": "用于显示于文章列表页，多个封面图用换行分隔",
            "type": "varchar",
            "key": false,
            "auto": "",
            "symbol": false,
            "fill_zero": false,
            "not_null": 0,
            "min_length": 0,
            "max_length": 255,
            "min": 0,
            "max": 0,
            "decimal": 0,
            "default": null,
            "map": ""
        },
        {
            "name": "title",
            "title": "标题",
            "description": "用于文章和html的title标签中",
            "type": "varchar",
            "key": true,
            "auto": "",
            "symbol": false,
            "fill_zero": false,
            "not_null": 1,
            "min_length": 0,
            "max_length": 125,
            "min": 0,
            "max": 0,
            "decimal": 0,
            "default": "",
            "map": ""
        },
        {
            "name": "available",
            "title": "是否启用",
            "description": "启用后前台才会显示该文章",
            "type": "tinyint",
            "key": false,
            "auto": "",
            "symbol": false,
            "fill_zero": false,
            "not_null": 1,
            "min_length": 0,
            "max_length": 1,
            "min": 0,
            "max": 1,
            "decimal": 0,
            "default": "1",
            "map": "0否|1是"
        },
        {
            "name": "state",
            "title": "状态",
            "description": "",
            "type": "smallint",
            "key": false,
            "auto": "",
            "symbol": false,
            "fill_zero": false,
            "not_null": 1,
            "min_length": 0,
            "max_length": 1,
            "min": 1,
            "max": 5,
            "decimal": 0,
            "default": "1",
            "map": "1正常|2推荐|3认证|4违规|5官方"
        },
        {
            "name": "channel_id",
            "title": "频道ID",
            "description": "该文章所属频道，仅该频道列表可以看到该文章",
            "type": "smallint",
            "key": false,
            "auto": "",
            "symbol": false,
            "fill_zero": false,
            "not_null": 1,
            "min_length": 0,
            "max_length": 5,
            "min": 0,
            "max": 10000,
            "decimal": 0,
            "default": "1",
            "map": "cms_article_channel.title"
        },
        {
            "name": "display",
            "title": "排序",
            "description": "决定文章显示的顺序",
            "type": "smallint",
            "key": false,
            "auto": "",
            "symbol": false,
            "fill_zero": false,
            "not_null": 1,
            "min_length": 0,
            "max_length": 5,
            "min": 0,
            "max": 10000,
            "decimal": 0,
            "default": "100",
            "map": ""
        },
        {
            "name": "user_id",
            "title": "用户ID",
            "description": "编辑这篇文章到本站的用户ID",
            "type": "mediumint",
            "key": false,
            "auto": "",
            "symbol": false,
            "fill_zero": false,
            "not_null": 1,
            "min_length": 0,
            "max_length": 8,
            "min": 0,
            "max": 8388607,
            "decimal": 0,
            "default": "0",
            "map": "user_account.phone.user_id"
        },
        {
            "name": "time_create",
            "title": "创建时间",
            "description": "",
            "type": "datetime",
            "key": false,
            "auto": "",
            "symbol": false,
            "fill_zero": false,
            "not_null": 1,
            "min_length": 0,
            "max_length": 0,
            "min": 0,
            "max": 0,
            "decimal": 0,
            "default": "CURRENT_TIMESTAMP",
            "map": ""
        },
        {
            "name": "time_update",
            "title": "更新时间",
            "description": "",
            "type": "timestamp",
            "key": false,
            "auto": "on update CURRENT_TIMESTAMP",
            "symbol": false,
            "fill_zero": false,
            "not_null": 1,
            "min_length": 0,
            "max_length": 0,
            "min": 0,
            "max": 0,
            "decimal": 0,
            "default": "CURRENT_TIMESTAMP",
            "map": ""
        },
        {
            "name": "description",
            "title": "描述",
            "description": "用于文章提纲和搜索引擎收录",
            "type": "varchar",
            "key": false,
            "auto": "",
            "symbol": false,
            "fill_zero": false,
            "not_null": 0,
            "min_length": 0,
            "max_length": 255,
            "min": 0,
            "max": 0,
            "decimal": 0,
            "default": null,
            "map": ""
        },
        {
            "name": "content",
            "title": "正文",
            "description": "文章的主体内容",
            "type": "longtext",
            "key": false,
            "auto": "",
            "symbol": false,
            "fill_zero": false,
            "not_null": 1,
            "min_length": 0,
            "max_length": 0,
            "min": 0,
            "max": 0,
            "decimal": 0,
            "default": "0",
            "map": ""
        }
    ]
}